adafruit_platformdetect/__init__.py
adafruit_platformdetect/board.py
adafruit_platformdetect/chip.py
adafruit_platformdetect/revcodes.py
adafruit_platformdetect/constants/__init__.py
adafruit_platformdetect/constants/boards.py
adafruit_platformdetect/constants/chips.py
Adafruit_PlatformDetect-3.70.0.dist-info/LICENSE
Adafruit_PlatformDetect-3.70.0.dist-info/METADATA
Adafruit_PlatformDetect-3.70.0.dist-info/WHEEL
Adafruit_PlatformDetect-3.70.0.dist-info/top_level.txt
Adafruit_PlatformDetect-3.70.0.dist-info/RECORD
